MANIFEST.in
README.rst
setup.cfg
setup.py
amigrations/__init__.py
amigrations/migrations.py
amigrations.egg-info/PKG-INFO
amigrations.egg-info/SOURCES.txt
amigrations.egg-info/dependency_links.txt
amigrations.egg-info/not-zip-safe
amigrations.egg-info/requires.txt
amigrations.egg-info/top_level.txt
amigrations/adapters/__init__.py
amigrations/adapters/base.py
amigrations/adapters/exceptions.py
amigrations/adapters/postgresql.py
amigrations/adapters/sqlite.py
amigrations/adapters/uri.py