Metadata-Version: 1.1
Name: amigrations
Version: 0.5
Summary: Ascetic database migrations. The most ease way to power your python app with raw database migrations
Home-page: https://github.com/sergeyglazyrindev/amigrations
Author: Sergey Glazyrin
Author-email: sergey.glazyrin.dev@gmail.com
License: MIT
Download-URL: https://github.com/sergeyglazyrindev/amigrations/tarball/0.5
Keywords: database,migration
Platform: UNKNOWN
Classifier: Development Status :: 4 - Beta
Classifier: License :: OSI Approved :: MIT License
Classifier: Programming Language :: Python :: 2.7
Classifier: Programming Language :: Python :: 3
Classifier: Programming Language :: Python :: 3.1
Classifier: Programming Language :: Python :: 3.2
Classifier: Programming Language :: Python :: 3.3
Classifier: Programming Language :: Python :: 3.4
Classifier: Programming Language :: Python :: 3.5
Classifier: Intended Audience :: Developers
Classifier: Topic :: Database
